CHANGELOG.md
cookiebanner/__init__.py
cookiebanner/locale/de/LC_MESSAGES/django.mo
cookiebanner/locale/de/LC_MESSAGES/django.po
cookiebanner/templates/cookiebanner/bootstrap4.html
cookiebanner/templates/cookiebanner/vanilla.html
cookiebanner/templatetags/cookiebanner.py
django_cookiebanner-0.2.8.dist-info/LICENSE
django_cookiebanner-0.2.8.dist-info/METADATA
django_cookiebanner-0.2.8.dist-info/WHEEL
django_cookiebanner-0.2.8.dist-info/RECORD
