Metadata-Version: 2.1
Name: django-cookiebanner
Version: 0.2.8
Summary: 
Home-page: https://github.com/sinnwerkstatt/django-cookiebanner
License: GPL-3.0+
Keywords: django,cookie,gdpr,dsgvo
Author: Andreas Nüßlein
Author-email: andreas@nuessle.in
Requires-Python: >=3.7
Classifier: License :: OSI Approved :: GNU General Public License v3 or later (GPLv3+)
Classifier: Programming Language :: Python :: 3
Classifier: Programming Language :: Python :: 3.7
Classifier: Programming Language :: Python :: 3.8
Classifier: Programming Language :: Python :: 3.9
Classifier: Programming Language :: Python :: 3.10
Classifier: Programming Language :: Python :: 3.11
Requires-Dist: django (>=3.2)
Project-URL: Repository, https://github.com/sinnwerkstatt/django-cookiebanner
